{
  "updatedAt": "2025-11-11T11:21:47.627Z",
  "count": 11,
  "data": {
    "관평동": {
      "pm10": 39,
      "pm25": 23,
      "dataTime": "2024-11-11 20:00"
    },
    "구성동": {
      "pm10": 27,
      "pm25": 14,
      "dataTime": "2024-11-11 20:00"
    },
    "대성동": {
      "pm10": 30,
      "pm25": 21,
      "dataTime": "2024-11-11 20:00"
    },
    "노은동": {
      "pm10": 27,
      "pm25": 18,
      "dataTime": "2024-11-11 20:00"
    },
    "둔산동": {
      "pm10": 40,
      "pm25": 26,
      "dataTime": "2024-11-11 20:00"
    },
    "문평동": {
      "pm10": 46,
      "pm25": 28,
      "dataTime": "2024-11-11 20:00"
    },
    "문창동": {
      "pm10": null,
      "pm25": null,
      "dataTime": "2024-11-11 20:00"
    },
    "상대동(대전)": {
      "pm10": 70,
      "pm25": 26,
      "dataTime": "2024-11-11 20:00"
    },
    "성남동1": {
      "pm10": 42,
      "pm25": 30,
      "dataTime": "2024-11-11 20:00"
    },
    "읍내동": {
      "pm10": 48,
      "pm25": 12,
      "dataTime": "2024-11-11 20:00"
    },
    "정림동": {
      "pm10": 44,
      "pm25": 20,
      "dataTime": "2024-11-11 20:00"
    }
  }
}
